main.py
helpers/crawler_api_client.py
helpers/datagouv_api_client.py
helpers/env_config.py
helpers/metrics_api_client.py
helpers/tabular_api_client.py
helpers/__pycache__/crawler_api_client.cpython-311.pyc
helpers/__pycache__/datagouv_api_client.cpython-311.pyc
helpers/__pycache__/env_config.cpython-311.pyc
helpers/__pycache__/metrics_api_client.cpython-311.pyc
helpers/__pycache__/tabular_api_client.cpython-311.pyc
iflow_mcp_datagouv_datagouv_mcp-0.2.14.dist-info/licenses/LICENSE
tests/__init__.py
tests/test_crawler_api.py
tests/test_datagouv_api.py
tests/test_env_config.py
tests/test_health_endpoint.py
tests/test_metrics_api.py
tests/test_tabular_api.py
tools/__init__.py
tools/download_and_parse_resource.py
tools/get_dataset_info.py
tools/get_metrics.py
tools/get_resource_info.py
tools/list_dataset_resources.py
tools/query_resource_data.py
tools/search_datasets.py
iflow_mcp_datagouv_datagouv_mcp-0.2.14.dist-info/METADATA
iflow_mcp_datagouv_datagouv_mcp-0.2.14.dist-info/WHEEL
iflow_mcp_datagouv_datagouv_mcp-0.2.14.dist-info/entry_points.txt
iflow_mcp_datagouv_datagouv_mcp-0.2.14.dist-info/top_level.txt
iflow_mcp_datagouv_datagouv_mcp-0.2.14.dist-info/RECORD
