Metadata-Version: 2.4
Name: iflow-mcp_datagouv_datagouv-mcp
Version: 0.2.14
Summary: Model Context Protocol (MCP) server for interacting with data.gouv.fr datasets and resources via LLM chatbots
Author: data.gouv.fr
Author-email: "data.gouv.fr" <opendatateam@data.gouv.fr>
Requires-Python: >=3.11,<4
License-File: LICENSE
Requires-Dist: httpx>=0.28.0
Requires-Dist: mcp<2,>=1.25.0
Dynamic: author
Dynamic: license-file
Dynamic: requires-python
